pycfdi_transform/__init__.py
pycfdi_transform/formatters/__init__.py
pycfdi_transform/formatters/efisco_corp_terceros_formatter.py
pycfdi_transform/formatters/formatter_interface.py
pycfdi_transform/formatters/catalogs/catalogs.py
pycfdi_transform/formatters/cfdi32/base_cfdi32_formatter.py
pycfdi_transform/formatters/cfdi32/efisco_core_cfdi32_formatter.py
pycfdi_transform/formatters/cfdi32/efisco_corp_cfdi32_formatter.py
pycfdi_transform/formatters/cfdi33/base_cfdi33_formatter.py
pycfdi_transform/formatters/cfdi33/efisco_core_cfdi33_formatter.py
pycfdi_transform/formatters/cfdi33/efisco_corp_cfdi33_formatter.py
pycfdi_transform/formatters/cfdi33/efisco_corp_erp_cfdi33_formatter.py
pycfdi_transform/formatters/cfdi40/base_cfdi40_formatter.py
pycfdi_transform/formatters/cfdi40/cda_cfdi40_formatter.py
pycfdi_transform/formatters/cfdi40/efisco_core_cfdi40_formatter.py
pycfdi_transform/formatters/cfdi40/efisco_corp_cfdi40_formatter.py
pycfdi_transform/formatters/cfdi40/efisco_corp_erp_cfdi40_formatter.py
pycfdi_transform/formatters/cfdis_relacionados/efisco_cfdis_relacionados_formatter.py
pycfdi_transform/formatters/concepts/efisco_concepts_detail_formatter.py
pycfdi_transform/formatters/concepts/efisco_concepts_detail_with_taxes_formatter.py
pycfdi_transform/formatters/iva_desglosado/efisco_corp_iva_desglosado_formatter.py
pycfdi_transform/formatters/nomina11/efisco_core_nomina11_formatter.py
pycfdi_transform/formatters/nomina11/efisco_nomina11_formatter.py
pycfdi_transform/formatters/nomina12/efisco_core_nomina12_formatter.py
pycfdi_transform/formatters/nomina12/efisco_corp_erp_nomina12_formatter.py
pycfdi_transform/formatters/nomina12/efisco_nomina12_formatter.py
pycfdi_transform/formatters/pagos10/efisco_pagos10_formatter.py
pycfdi_transform/formatters/pagos20/efisco_corp_erp_pagos20_formatter.py
pycfdi_transform/formatters/pagos20/efisco_pagos20_formatter.py
pycfdi_transform/helpers/schema_helper.py
pycfdi_transform/helpers/string_helper.py
pycfdi_transform-0.1.14.3.dist-info/METADATA
pycfdi_transform-0.1.14.3.dist-info/WHEEL
pycfdi_transform-0.1.14.3.dist-info/top_level.txt
pycfdi_transform-0.1.14.3.dist-info/RECORD
