Metadata-Version: 2.1
Name: pycfdi-transform
Version: 0.1.14.3
Summary: Cfdi Xml Transformation column format/csv
Home-page: https://github.com/swsapien/pycfdi-transform
Author: SW sapien
License: MIT
Classifier: Programming Language :: Python :: 3
Classifier: License :: OSI Approved :: MIT License
Classifier: Operating System :: OS Independent
Requires-Python: >=3.9
Requires-Dist: XlsxWriter
Requires-Dist: xlwt
Requires-Dist: lxml
